[
  {
    "_id": {
      "$oid": "62a3f587102e921da1253d32"
    },
    "Name": "House Down Payment",
    "TargetAmount": 100000,
    "TargetDate": {
      "$date": {
        "$numberLong": "1736312400000"
      }
    },
    "Balance": 73501.82,
    "Created": {
      "$date": {
        "$numberLong": "1654912390857"
      }
    },
    "TransactionIds": null,
    "TagIds": null,
    "UserId": {
      "$oid": "62a29c15f4605c4c9fa7f306"
    }
  },
  {
    "_id": {
      "$oid": "62a3f5e0102e921da1253d33"
    },
    "Name": "Tesla Model Y",
    "TargetAmount": 60000,
    "TargetDate": {
      "$date": {
        "$numberLong": "1662004800000"
      }
    },
    "Balance": 43840.02,
    "Created": {
      "$date": {
        "$numberLong": "1654912480950"
      }
    },
    "TransactionIds": null,
    "TagIds": null,
    "UserId": {
      "$oid": "62a29c15f4605c4c9fa7f306"
    }
  },
  {
    "_id": {
      "$oid": "62a3f62e102e921da1253d34"
    },
    "Name": "Trip to London",
    "TargetAmount": 3500,
    "TargetDate": {
      "$date": {
        "$numberLong": "1659412800000"
      }
    },
    "Created": {
      "$date": {
        "$numberLong": "1654912558236"
      }
    },
    "TransactionIds": null,
    "TagIds": null,
    "Balance": 753.89,
    "UserId": {
      "$oid": "62a29c15f4605c4c9fa7f306"
    }
  },
  {
    "_id": {
      "$oid": "62a61945fa15f1cd18516a5f"
    },
    "Name": "Trip to NYC",
    "TargetAmount": 800,
    "TargetDate": {
      "$date": {
        "$numberLong": "1702184400000"
      }
    },
    "Balance": 0,
    "Created": {
      "$date": {
        "$numberLong": "1655053065668"
      }
    },
    "TransactionIds": null,
    "TagIds": null,
    "UserId": {
      "$oid": "62a29c15f4605c4c9fa7f306"
    }
  }
]